pplyr/__init__.py
pplyr/_nbdev.py
pplyr/core.py
pplyr-0.0.5.dist-info/DESCRIPTION.rst
pplyr-0.0.5.dist-info/METADATA
pplyr-0.0.5.dist-info/RECORD
pplyr-0.0.5.dist-info/WHEEL
pplyr-0.0.5.dist-info/entry_points.txt
pplyr-0.0.5.dist-info/metadata.json
pplyr-0.0.5.dist-info/top_level.txt
