Metadata-Version: 2.0
Name: pplyr
Version: 0.0.5
Summary: use the R dplyr package with python
Home-page: https://github.com/fdewes/pplyr
Author: Florian Dewes
Author-email: fdewes@beuth-hochschule.de
License: Apache Software License 2.0
Keywords: d,p,l,y,r,,, ,p,p,l,y,r
Platform: UNKNOWN
Classifier: Development Status :: 4 - Beta
Classifier: Intended Audience :: Science/Research
Classifier: License :: OSI Approved :: Apache Software License
Classifier: Natural Language :: English
Classifier: Programming Language :: Python :: 3.6
Classifier: Programming Language :: Python :: 3.7
Classifier: Programming Language :: Python :: 3.8
Requires-Python: >=3.6
